plotly_flex/LF.py
plotly_flex/__init__.py
plotly_flex/scalable_figure.py
plotly_flex/scalable_figure_interface.py
plotly_flex/utils.py
plotly_flex/trace/__init__.py
plotly_flex/trace/mapping.py
plotly_flex/trace/scalable_trace_interface.py
plotly_flex/trace/trace_bar.py
plotly_flex/trace/trace_box.py
plotly_flex/trace/trace_histogram.py
plotly_flex/trace/trace_pie.py
plotly_flex/trace/trace_scatter.py
plotly_flex/trace/utils.py
plotly_flex-0.1.0a2.dist-info/licenses/LICENSE
plotly_flex-0.1.0a2.dist-info/METADATA
plotly_flex-0.1.0a2.dist-info/WHEEL
plotly_flex-0.1.0a2.dist-info/top_level.txt
plotly_flex-0.1.0a2.dist-info/RECORD
