Metadata-Version: 2.4
Name: plotly-flex
Version: 0.1.0a2
Summary: Visualizing large datasets with plotly by using polars as backend.
Author-email: Flex Analytics <info@flexanalytics.pro>, Jeroen Van Der Donckt <jeroen@flexanalytics.pro>
License-Expression: AGPL-3.0
Project-URL: Homepage, https://flexanalytics.pro
Project-URL: Repository, https://github.com/flex-analytics/plotly-flex
Keywords: big-data,visualization,plotly,plotly-dash,polars
Classifier: Programming Language :: Python
Classifier: Programming Language :: Python :: 3
Classifier: Programming Language :: Python :: 3.9
Classifier: Programming Language :: Python :: 3.10
Classifier: Programming Language :: Python :: 3.11
Classifier: Programming Language :: Python :: 3.12
Classifier: Programming Language :: Python :: 3.13
Classifier: Operating System :: POSIX :: Linux
Classifier: Operating System :: MacOS :: MacOS X
Classifier: Operating System :: Microsoft :: Windows
Requires-Python: <3.14,>=3.9
License-File: LICENSE
Requires-Dist: dash>=2.18.2
Requires-Dist: numpy>=2.0.2
Requires-Dist: orjson>=3.10.15
Requires-Dist: plotly>=6.0.0
Requires-Dist: polars>=1.27.1
Provides-Extra: widget
Requires-Dist: anywidget>=0.9.13; extra == "widget"
Dynamic: license-file
